converter/Converter.py
converter/__init__.py
converter/aruba/__init__.py
converter/aruba/parser/ArubaProjectParser.py
converter/aruba/parser/__init__.py
emitter/__init__.py
emitter/deployment/MapHierarchyDeployer.py
emitter/deployment/__init__.py
emitter/persistance/__init__.py
model/__init__.py
model/network/AccessPoint.py
model/network/PAP.py
model/network/__init__.py
dnac_maps-0.0.2.dist-info/LICENSE
dnac_maps-0.0.2.dist-info/METADATA
dnac_maps-0.0.2.dist-info/WHEEL
dnac_maps-0.0.2.dist-info/top_level.txt
dnac_maps-0.0.2.dist-info/RECORD
