Metadata-Version: 2.1
Name: dnac-maps
Version: 0.0.2
Summary: Wireless Map Export
Home-page: UNKNOWN
Author: Rk Somasundaram
Author-email: rks@cisco.com
License: UNKNOWN
Platform: UNKNOWN
Classifier: Programming Language :: Python :: 3
Classifier: License :: OSI Approved :: MIT License
Classifier: Operating System :: OS Independent
Requires-Python: >=3.6
